conan_client_remote_s3/__init__.py
conan_client_remote_s3/logger.py
conan_client_remote_s3-0.0.6.dist-info/LICENSE
conan_client_remote_s3-0.0.6.dist-info/METADATA
conan_client_remote_s3-0.0.6.dist-info/WHEEL
conan_client_remote_s3-0.0.6.dist-info/entry_points.txt
conan_client_remote_s3-0.0.6.dist-info/top_level.txt
conan_client_remote_s3-0.0.6.dist-info/RECORD
