Metadata-Version: 2.1
Name: conan-client-remote-s3
Version: 0.0.6
Summary: Serverless Conan remote storing packages in S3 bucket
Home-page: https://github.com/kshpytsya/conan-client-remote-s3
Author: Kyrylo Shpytsya
Author-email: kshpitsa@gmail.com
License: MIT License
Platform: UNKNOWN
Classifier: License :: OSI Approved :: MIT License
Requires-Python: >=3.6
License-File: LICENSE
Requires-Dist: boto3 (<2,>=1.13.23)
Requires-Dist: requests-adapter-injector (<1,>=0.0.5)
Requires-Dist: requests-wsgi-adapter (<1,>=0.4.1)
Requires-Dist: werkzeug (<2,>=1.0.1)
